[
  {
    "id": "__ueErjneO-None",
    "etr": "2025-08-06T05:00:00Z",
    "etrConfidence": null,
    "cluster": false,
    "comments": "An outage has been reported in your area. We are working to determine a restoration time.",
    "cause": null,
    "numberOut": 1,
    "custAffected": 4,
    "crewStatus": null,
    "startTime": null,
    "latitude": 32.55296,
    "longitude": -84.94778,
    "source": "https://kubra.io/cluster-data/133/f738adb9-3478-457e-9af5-fc3b91ec6aec/4b67048e-c851-4ada-93f3-dfafe53d10ab/public/cluster-2/032002331.json"
  },
  {
    "id": "cmleEhsaeO-None",
    "etr": "ETR-NULL",
    "etrConfidence": null,
    "cluster": false,
    "comments": "An outage has been reported in your area. We are working to determine a restoration time.",
    "cause": null,
    "numberOut": 1,
    "custAffected": 4,
    "crewStatus": null,
    "startTime": null,
    "latitude": 32.50914,
    "longitude": -84.88261,
    "source": "https://kubra.io/cluster-data/103/f738adb9-3478-457e-9af5-fc3b91ec6aec/4b67048e-c851-4ada-93f3-dfafe53d10ab/public/cluster-2/03200233301.json"
  },
  {
    "id": "gwgeEpcmeO-None",
    "etr": "ETR-EXP",
    "etrConfidence": null,
    "cluster": false,
    "comments": "An outage has been reported in your area. We are working to determine a restoration time.",
    "cause": null,
    "numberOut": 1,
    "custAffected": 4,
    "crewStatus": null,
    "startTime": null,
    "latitude": 32.48516,
    "longitude": -84.94153,
    "source": "https://kubra.io/cluster-data/003/f738adb9-3478-457e-9af5-fc3b91ec6aec/4b67048e-c851-4ada-93f3-dfafe53d10ab/public/cluster-2/03200233300.json"
  },
  {
    "id": "gxxdEpzmeO-None",
    "etr": "2025-08-06T05:00:00Z",
    "etrConfidence": null,
    "cluster": false,
    "comments": "An outage has been reported in your area. We are working to determine a restoration time.",
    "cause": null,
    "numberOut": 1,
    "custAffected": 84,
    "crewStatus": null,
    "startTime": null,
    "latitude": 32.40852,
    "longitude": -84.94521,
    "source": "https://kubra.io/cluster-data/332/f738adb9-3478-457e-9af5-fc3b91ec6aec/4b67048e-c851-4ada-93f3-dfafe53d10ab/public/cluster-2/03200233.json"
  },
  {
    "id": "y{beEvojeO-None",
    "etr": "ETR-EXP",
    "etrConfidence": null,
    "cluster": false,
    "comments": "An outage has been reported in your area. We are working to determine a restoration time.",
    "cause": null,
    "numberOut": 1,
    "custAffected": 4,
    "crewStatus": null,
    "startTime": null,
    "latitude": 32.46029,
    "longitude": -84.92812,
    "source": "https://kubra.io/cluster-data/003/f738adb9-3478-457e-9af5-fc3b91ec6aec/4b67048e-c851-4ada-93f3-dfafe53d10ab/public/cluster-2/03200233300.json"
  },
  {
    "id": "{`mnEdf`|N-None",
    "etr": "ETR-EXP",
    "etrConfidence": null,
    "cluster": false,
    "comments": "An outage has been reported in your area. We are working to determine a restoration time.",
    "cause": null,
    "numberOut": 1,
    "custAffected": 4,
    "crewStatus": null,
    "startTime": null,
    "latitude": 33.98686,
    "longitude": -83.40083,
    "source": "https://kubra.io/cluster-data/201/f738adb9-3478-457e-9af5-fc3b91ec6aec/4b67048e-c851-4ada-93f3-dfafe53d10ab/public/cluster-2/03200320121102.json"
  },
  {
    "id": "_}lnEvx_|N-None",
    "etr": "ETR-NULL",
    "etrConfidence": null,
    "cluster": false,
    "comments": "An outage has been reported in your area. We are working to determine a restoration time.",
    "cause": null,
    "numberOut": 1,
    "custAffected": 4,
    "crewStatus": null,
    "startTime": null,
    "latitude": 33.98624,
    "longitude": -83.39868,
    "source": "https://kubra.io/cluster-data/201/f738adb9-3478-457e-9af5-fc3b91ec6aec/4b67048e-c851-4ada-93f3-dfafe53d10ab/public/cluster-2/03200320121102.json"
  },
  {
    "id": "wjknEhbt~N-None",
    "etr": "2025-08-06T08:30:00Z",
    "etrConfidence": null,
    "cluster": false,
    "comments": "An outage has been reported in your area. We are working to determine a restoration time.",
    "cause": null,
    "numberOut": 1,
    "custAffected": 4,
    "crewStatus": null,
    "startTime": null,
    "latitude": 33.9782,
    "longitude": -83.83029,
    "source": "https://kubra.io/cluster-data/230/f738adb9-3478-457e-9af5-fc3b91ec6aec/4b67048e-c851-4ada-93f3-dfafe53d10ab/public/cluster-2/0320032.json"
  },
  {
    "id": "qjfnElo}|N-None",
    "etr": "ETR-EXP",
    "etrConfidence": null,
    "cluster": false,
    "comments": "An outage has been reported in your area. We are working to determine a restoration time.",
    "cause": null,
    "numberOut": 1,
    "custAffected": 38,
    "crewStatus": null,
    "startTime": null,
    "latitude": 33.95257,
    "longitude": -83.55079,
    "source": "https://kubra.io/cluster-data/023/f738adb9-3478-457e-9af5-fc3b91ec6aec/4b67048e-c851-4ada-93f3-dfafe53d10ab/public/cluster-2/03200320.json"
  },
  {
    "id": "yofmEt{p|N-None",
    "etr": "ETR-EXP",
    "etrConfidence": null,
    "cluster": false,
    "comments": "An outage has been reported in your area. We are working to determine a restoration time.",
    "cause": null,
    "numberOut": 1,
    "custAffected": 4,
    "crewStatus": null,
    "startTime": null,
    "latitude": 33.78957,
    "longitude": -83.48619,
    "source": "https://kubra.io/cluster-data/023/f738adb9-3478-457e-9af5-fc3b91ec6aec/4b67048e-c851-4ada-93f3-dfafe53d10ab/public/cluster-2/03200320.json"
  },
  {
    "id": "wrwnEfwtyN-None",
    "etr": "ETR-NULL",
    "etrConfidence": null,
    "cluster": false,
    "comments": "An outage has been reported in your area. We are working to determine a restoration time.",
    "cause": null,
    "numberOut": 1,
    "custAffected": 4,
    "crewStatus": null,
    "startTime": null,
    "latitude": 34.04092,
    "longitude": -83.01444,
    "source": "https://kubra.io/cluster-data/230/f738adb9-3478-457e-9af5-fc3b91ec6aec/4b67048e-c851-4ada-93f3-dfafe53d10ab/public/cluster-2/0320032.json"
  },
  {
    "id": "icwnEttzzN-None",
    "etr": "2025-08-06T13:00:00Z",
    "etrConfidence": null,
    "cluster": false,
    "comments": "An outage has been reported in your area. We are working to determine a restoration time.",
    "cause": null,
    "numberOut": 1,
    "custAffected": 4,
    "crewStatus": null,
    "startTime": null,
    "latitude": 34.03845,
    "longitude": -83.20859,
    "source": "https://kubra.io/cluster-data/023/f738adb9-3478-457e-9af5-fc3b91ec6aec/4b67048e-c851-4ada-93f3-dfafe53d10ab/public/cluster-2/03200320.json"
  },
  {
    "id": "wdmnEr{f|N-None",
    "etr": "2025-08-06T06:15:00Z",
    "etrConfidence": null,
    "cluster": false,
    "comments": "An outage has been reported in your area. We are working to determine a restoration time.",
    "cause": null,
    "numberOut": 1,
    "custAffected": 4,
    "crewStatus": null,
    "startTime": null,
    "latitude": 33.98748,
    "longitude": -83.43498,
    "source": "https://kubra.io/cluster-data/210/f738adb9-3478-457e-9af5-fc3b91ec6aec/4b67048e-c851-4ada-93f3-dfafe53d10ab/public/cluster-2/0320032012.json"
  },
  {
    "id": "e}npE|bpzN-None",
    "etr": "ETR-EXP",
    "etrConfidence": null,
    "cluster": false,
    "comments": "An outage has been reported in your area. We are working to determine a restoration time.",
    "cause": null,
    "numberOut": 1,
    "custAffected": 4,
    "crewStatus": null,
    "startTime": null,
    "latitude": 34.32419,
    "longitude": -83.15455,
    "source": "https://kubra.io/cluster-data/030/f738adb9-3478-457e-9af5-fc3b91ec6aec/4b67048e-c851-4ada-93f3-dfafe53d10ab/public/cluster-2/0320030.json"
  },
  {
    "id": "gm|qElvr{N-None",
    "etr": "2025-08-06T07:30:00Z",
    "etrConfidence": null,
    "cluster": false,
    "comments": "An outage has been reported in your area. We are working to determine a restoration time.",
    "cause": null,
    "numberOut": 1,
    "custAffected": 21,
    "crewStatus": null,
    "startTime": null,
    "latitude": 34.55716,
    "longitude": -83.33175,
    "source": "https://kubra.io/cluster-data/030/f738adb9-3478-457e-9af5-fc3b91ec6aec/4b67048e-c851-4ada-93f3-dfafe53d10ab/public/cluster-2/0320030.json"
  },
  {
    "id": "cbopExfm~N-None",
    "etr": "ETR-EXP",
    "etrConfidence": null,
    "cluster": false,
    "comments": "An outage has been reported in your area. We are working to determine a restoration time.",
    "cause": null,
    "numberOut": 1,
    "custAffected": 4,
    "crewStatus": null,
    "startTime": null,
    "latitude": 34.32498,
    "longitude": -83.79517,
    "source": "https://kubra.io/cluster-data/030/f738adb9-3478-457e-9af5-fc3b91ec6aec/4b67048e-c851-4ada-93f3-dfafe53d10ab/public/cluster-2/0320030.json"
  },
  {
    "id": "ozqkEv}daO-None",
    "etr": "ETR-NULL",
    "etrConfidence": null,
    "cluster": false,
    "comments": "An outage has been reported in your area. We are working to determine a restoration time.",
    "cause": null,
    "numberOut": 1,
    "custAffected": 4,
    "crewStatus": null,
    "startTime": null,
    "latitude": 33.51992,
    "longitude": -84.24428,
    "source": "https://kubra.io/cluster-data/202/f738adb9-3478-457e-9af5-fc3b91ec6aec/4b67048e-c851-4ada-93f3-dfafe53d10ab/public/cluster-2/03200320202.json"
  },
  {
    "id": "qspoEzqh`O-None",
    "etr": "2025-08-06T08:30:00Z",
    "etrConfidence": null,
    "cluster": false,
    "comments": "An outage has been reported in your area. We are working to determine a restoration time.",
    "cause": null,
    "numberOut": 1,
    "custAffected": 6,
    "crewStatus": null,
    "startTime": null,
    "latitude": 34.16905,
    "longitude": -84.09902,
    "source": "https://kubra.io/cluster-data/023/f738adb9-3478-457e-9af5-fc3b91ec6aec/4b67048e-c851-4ada-93f3-dfafe53d10ab/public/cluster-2/03200320.json"
  },
  {
    "id": "sbunErqk`O-None",
    "etr": "2025-08-06T08:30:00Z",
    "etrConfidence": null,
    "cluster": false,
    "comments": "An outage has been reported in your area. We are working to determine a restoration time.",
    "cause": null,
    "numberOut": 1,
    "custAffected": 6,
    "crewStatus": null,
    "startTime": null,
    "latitude": 34.0281,
    "longitude": -84.11434,
    "source": "https://kubra.io/cluster-data/023/f738adb9-3478-457e-9af5-fc3b91ec6aec/4b67048e-c851-4ada-93f3-dfafe53d10ab/public/cluster-2/03200320.json"
  },
  {
    "id": "i`ymExiq`O-None",
    "etr": "ETR-EXP",
    "etrConfidence": null,
    "cluster": false,
    "comments": "An outage has been reported in your area. We are working to determine a restoration time.",
    "cause": null,
    "numberOut": 1,
    "custAffected": 4,
    "crewStatus": null,
    "startTime": null,
    "latitude": 33.88437,
    "longitude": -84.14381,
    "source": "https://kubra.io/cluster-data/002/f738adb9-3478-457e-9af5-fc3b91ec6aec/4b67048e-c851-4ada-93f3-dfafe53d10ab/public/cluster-2/032003200.json"
  },
  {
    "id": "uabkE|ln`O-None",
    "etr": "2025-08-06T06:15:00Z",
    "etrConfidence": null,
    "cluster": false,
    "comments": "Repair work required an outage. We are working to restore power as quickly as possible.",
    "cause": null,
    "numberOut": 1,
    "custAffected": 9,
    "crewStatus": null,
    "startTime": null,
    "latitude": 33.43915,
    "longitude": -84.12895,
    "source": "https://kubra.io/cluster-data/202/f738adb9-3478-457e-9af5-fc3b91ec6aec/4b67048e-c851-4ada-93f3-dfafe53d10ab/public/cluster-2/032003202.json"
  },
  {
    "id": "_{llEhcu`O-None",
    "etr": "ETR-NULL",
    "etrConfidence": null,
    "cluster": false,
    "comments": "An outage has been reported in your area. We are working to determine a restoration time.",
    "cause": null,
    "numberOut": 1,
    "custAffected": 4,
    "crewStatus": null,
    "startTime": null,
    "latitude": 33.65824,
    "longitude": -84.16325,
    "source": "https://kubra.io/cluster-data/023/f738adb9-3478-457e-9af5-fc3b91ec6aec/4b67048e-c851-4ada-93f3-dfafe53d10ab/public/cluster-2/03200320.json"
  },
  {
    "id": "_gmmEvtw`O-None",
    "etr": "2025-08-06T05:00:00Z",
    "etrConfidence": null,
    "cluster": false,
    "comments": "An outage has been reported in your area. We are working to determine a restoration time.",
    "cause": null,
    "numberOut": 1,
    "custAffected": 4,
    "crewStatus": null,
    "startTime": null,
    "latitude": 33.824,
    "longitude": -84.17628,
    "source": "https://kubra.io/cluster-data/200/f738adb9-3478-457e-9af5-fc3b91ec6aec/4b67048e-c851-4ada-93f3-dfafe53d10ab/public/cluster-2/0320032002.json"
  },
  {
    "id": "mvenErpibO-None",
    "etr": "2025-08-06T06:30:00Z",
    "etrConfidence": null,
    "cluster": false,
    "comments": "An incident caused an outage in your area. We are working to restore power as quickly as possible.",
    "cause": null,
    "numberOut": 1,
    "custAffected": 272,
    "crewStatus": null,
    "startTime": null,
    "latitude": 33.94935,
    "longitude": -84.43162,
    "source": "https://kubra.io/cluster-data/113/f738adb9-3478-457e-9af5-fc3b91ec6aec/4b67048e-c851-4ada-93f3-dfafe53d10ab/public/cluster-2/032002311.json"
  },
  {
    "id": "{yxlEjsacO-None",
    "etr": "2025-08-06T06:00:00Z",
    "etrConfidence": null,
    "cluster": false,
    "comments": "An outage has been reported in your area. We are working to determine a restoration time.",
    "cause": null,
    "numberOut": 1,
    "custAffected": 5,
    "crewStatus": null,
    "startTime": null,
    "latitude": 33.7195,
    "longitude": -84.55494,
    "source": "https://kubra.io/cluster-data/320/f738adb9-3478-457e-9af5-fc3b91ec6aec/4b67048e-c851-4ada-93f3-dfafe53d10ab/public/cluster-2/0320023.json"
  },
  {
    "id": "kulmEpwlbO-None",
    "etr": "ETR-NULL",
    "etrConfidence": null,
    "cluster": false,
    "comments": "An outage has been reported in your area. We are working to determine a restoration time.",
    "cause": null,
    "numberOut": 1,
    "custAffected": 4,
    "crewStatus": null,
    "startTime": null,
    "latitude": 33.82118,
    "longitude": -84.44809,
    "source": "https://kubra.io/cluster-data/113/f738adb9-3478-457e-9af5-fc3b91ec6aec/4b67048e-c851-4ada-93f3-dfafe53d10ab/public/cluster-2/032002311.json"
  },
  {
    "id": "ypbmEhs_aO-None",
    "etr": "2025-08-06T12:00:00Z",
    "etrConfidence": null,
    "cluster": false,
    "comments": "A tree has caused a power outage in your area. Most customers will be restored by the ERT shown.",
    "cause": null,
    "numberOut": 1,
    "custAffected": 424,
    "crewStatus": null,
    "startTime": null,
    "latitude": 33.76925,
    "longitude": -84.21701,
    "source": "https://kubra.io/cluster-data/200/f738adb9-3478-457e-9af5-fc3b91ec6aec/4b67048e-c851-4ada-93f3-dfafe53d10ab/public/cluster-2/0320032002.json"
  },
  {
    "id": "o{slErncaO-None",
    "etr": "2025-08-06T06:45:00Z",
    "etrConfidence": null,
    "cluster": false,
    "comments": "An outage has been reported in your area. We are working to determine a restoration time.",
    "cause": null,
    "numberOut": 1,
    "custAffected": 4,
    "crewStatus": null,
    "startTime": null,
    "latitude": 33.69416,
    "longitude": -84.23674,
    "source": "https://kubra.io/cluster-data/020/f738adb9-3478-457e-9af5-fc3b91ec6aec/4b67048e-c851-4ada-93f3-dfafe53d10ab/public/cluster-2/0320032020.json"
  },
  {
    "id": "snrlErr|`O-None",
    "etr": "2025-08-06T06:45:00Z",
    "etrConfidence": null,
    "cluster": false,
    "comments": "An outage has been reported in your area. We are working to determine a restoration time.",
    "cause": null,
    "numberOut": 1,
    "custAffected": 4,
    "crewStatus": null,
    "startTime": null,
    "latitude": 33.68698,
    "longitude": -84.20154,
    "source": "https://kubra.io/cluster-data/020/f738adb9-3478-457e-9af5-fc3b91ec6aec/4b67048e-c851-4ada-93f3-dfafe53d10ab/public/cluster-2/0320032020.json"
  },
  {
    "id": "mcskE`ixaO-None",
    "etr": "2025-08-06T07:15:00Z",
    "etrConfidence": null,
    "cluster": true,
    "comments": null,
    "cause": null,
    "numberOut": 2,
    "custAffected": 5,
    "crewStatus": null,
    "startTime": null,
    "latitude": 33.52647,
    "longitude": -84.34337,
    "source": "https://kubra.io/cluster-data/120/f738adb9-3478-457e-9af5-fc3b91ec6aec/4b67048e-c851-4ada-93f3-dfafe53d10ab/public/cluster-2/03200320202021.json"
  },
  {
    "id": "cfkkEbwcaO-None",
    "etr": "ETR-EXP",
    "etrConfidence": null,
    "cluster": false,
    "comments": "An outage has been reported in your area. We are working to determine a restoration time.",
    "cause": null,
    "numberOut": 1,
    "custAffected": 4,
    "crewStatus": null,
    "startTime": null,
    "latitude": 33.48594,
    "longitude": -84.2381,
    "source": "https://kubra.io/cluster-data/020/f738adb9-3478-457e-9af5-fc3b91ec6aec/4b67048e-c851-4ada-93f3-dfafe53d10ab/public/cluster-2/0320032020.json"
  },
  {
    "id": "eq|cEtqp|N-None",
    "etr": "2025-08-06T13:00:00Z",
    "etrConfidence": null,
    "cluster": false,
    "comments": "An outage has been reported in your area. We are working to determine a restoration time.",
    "cause": null,
    "numberOut": 1,
    "custAffected": 4,
    "crewStatus": null,
    "startTime": null,
    "latitude": 32.26403,
    "longitude": -83.48459,
    "source": "https://kubra.io/cluster-data/230/f738adb9-3478-457e-9af5-fc3b91ec6aec/4b67048e-c851-4ada-93f3-dfafe53d10ab/public/cluster-2/0320032.json"
  },
  {
    "id": "az}gEdavaO-None",
    "etr": "ETR-EXP",
    "etrConfidence": null,
    "cluster": false,
    "comments": "An outage has been reported in your area. We are working to determine a restoration time.",
    "cause": null,
    "numberOut": 1,
    "custAffected": 4,
    "crewStatus": null,
    "startTime": null,
    "latitude": 32.92593,
    "longitude": -84.33187,
    "source": "https://kubra.io/cluster-data/230/f738adb9-3478-457e-9af5-fc3b91ec6aec/4b67048e-c851-4ada-93f3-dfafe53d10ab/public/cluster-2/0320032.json"
  },
  {
    "id": "ky{kEnrjfO-None",
    "etr": "ETR-EXP",
    "etrConfidence": null,
    "cluster": false,
    "comments": "An outage has been reported in your area. We are working to determine a restoration time.",
    "cause": null,
    "numberOut": 1,
    "custAffected": 4,
    "crewStatus": null,
    "startTime": null,
    "latitude": 33.57094,
    "longitude": -85.0924,
    "source": "https://kubra.io/cluster-data/320/f738adb9-3478-457e-9af5-fc3b91ec6aec/4b67048e-c851-4ada-93f3-dfafe53d10ab/public/cluster-2/0320023.json"
  },
  {
    "id": "wc}oEhgfgO-None",
    "etr": "ETR-EXP",
    "etrConfidence": null,
    "cluster": false,
    "comments": "An outage has been reported in your area. We are working to determine a restoration time.",
    "cause": null,
    "numberOut": 1,
    "custAffected": 4,
    "crewStatus": null,
    "startTime": null,
    "latitude": 34.23308,
    "longitude": -85.23397,
    "source": "https://kubra.io/cluster-data/320/f738adb9-3478-457e-9af5-fc3b91ec6aec/4b67048e-c851-4ada-93f3-dfafe53d10ab/public/cluster-2/0320023.json"
  },
  {
    "id": "eyraEbsifO-None",
    "etr": "2025-08-06T07:30:00Z",
    "etrConfidence": null,
    "cluster": false,
    "comments": "An outage has been reported in your area. We are working to determine a restoration time.",
    "cause": null,
    "numberOut": 1,
    "custAffected": 4,
    "crewStatus": null,
    "startTime": null,
    "latitude": 31.88643,
    "longitude": -85.08738,
    "source": "https://kubra.io/cluster-data/102/f738adb9-3478-457e-9af5-fc3b91ec6aec/4b67048e-c851-4ada-93f3-dfafe53d10ab/public/cluster-2/0320201.json"
  },
  {
    "id": "_lgbEppmlN-None",
    "etr": "2025-08-06T13:00:00Z",
    "etrConfidence": null,
    "cluster": false,
    "comments": "An outage has been reported in your area. We are working to determine a restoration time.",
    "cause": null,
    "numberOut": 1,
    "custAffected": 4,
    "crewStatus": null,
    "startTime": null,
    "latitude": 31.99184,
    "longitude": -80.84761,
    "source": "https://kubra.io/cluster-data/330/f738adb9-3478-457e-9af5-fc3b91ec6aec/4b67048e-c851-4ada-93f3-dfafe53d10ab/public/cluster-2/0320033.json"
  },
  {
    "id": "avghE`{}tN-None",
    "etr": "ETR-NULL",
    "etrConfidence": null,
    "cluster": false,
    "comments": "An outage has been reported in your area. We are working to determine a restoration time.",
    "cause": null,
    "numberOut": 1,
    "custAffected": 4,
    "crewStatus": null,
    "startTime": null,
    "latitude": 32.97649,
    "longitude": -82.24193,
    "source": "https://kubra.io/cluster-data/323/f738adb9-3478-457e-9af5-fc3b91ec6aec/4b67048e-c851-4ada-93f3-dfafe53d10ab/public/cluster-2/03200323.json"
  },
  {
    "id": "oe~hEn_ltN-None",
    "etr": "ETR-EXP",
    "etrConfidence": null,
    "cluster": false,
    "comments": "Emergency repairs required an outage. We are working to restore power as quickly as possible.",
    "cause": null,
    "numberOut": 1,
    "custAffected": 4,
    "crewStatus": null,
    "startTime": null,
    "latitude": 33.0916,
    "longitude": -82.15048,
    "source": "https://kubra.io/cluster-data/323/f738adb9-3478-457e-9af5-fc3b91ec6aec/4b67048e-c851-4ada-93f3-dfafe53d10ab/public/cluster-2/03200323.json"
  },
  {
    "id": "yopcEv{qnN-None",
    "etr": "ETR-EXP",
    "etrConfidence": null,
    "cluster": false,
    "comments": "Severe weather caused widespread outages. Power to most customers will be restored by the ERT shown.",
    "cause": null,
    "numberOut": 1,
    "custAffected": 10,
    "crewStatus": null,
    "startTime": null,
    "latitude": 32.20237,
    "longitude": -81.19756,
    "source": "https://kubra.io/cluster-data/032/f738adb9-3478-457e-9af5-fc3b91ec6aec/4b67048e-c851-4ada-93f3-dfafe53d10ab/public/cluster-2/03200332230.json"
  },
  {
    "id": "kvnbErdwnN-None",
    "etr": "ETR-EXP",
    "etrConfidence": null,
    "cluster": false,
    "comments": "An outage has been reported in your area. We are working to determine a restoration time.",
    "cause": null,
    "numberOut": 1,
    "custAffected": 41,
    "crewStatus": null,
    "startTime": null,
    "latitude": 32.02934,
    "longitude": -81.22458,
    "source": "https://kubra.io/cluster-data/223/f738adb9-3478-457e-9af5-fc3b91ec6aec/4b67048e-c851-4ada-93f3-dfafe53d10ab/public/cluster-2/032003322.json"
  },
  {
    "id": "enocEdnloN-None",
    "etr": "ETR-EXP",
    "etrConfidence": null,
    "cluster": false,
    "comments": "An outage has been reported in your area. We are working to determine a restoration time.",
    "cause": null,
    "numberOut": 1,
    "custAffected": 108,
    "crewStatus": null,
    "startTime": null,
    "latitude": 32.19699,
    "longitude": -81.33363,
    "source": "https://kubra.io/cluster-data/122/f738adb9-3478-457e-9af5-fc3b91ec6aec/4b67048e-c851-4ada-93f3-dfafe53d10ab/public/cluster-2/03200332221.json"
  },
  {
    "id": "omdcEpxeoN-None",
    "etr": "2025-08-06T05:00:00Z",
    "etrConfidence": null,
    "cluster": false,
    "comments": "An outage has been reported in your area. We are working to determine a restoration time.",
    "cause": null,
    "numberOut": 1,
    "custAffected": 7,
    "crewStatus": null,
    "startTime": null,
    "latitude": 32.14056,
    "longitude": -81.29945,
    "source": "https://kubra.io/cluster-data/122/f738adb9-3478-457e-9af5-fc3b91ec6aec/4b67048e-c851-4ada-93f3-dfafe53d10ab/public/cluster-2/03200332221.json"
  },
  {
    "id": "wjsbEvqenN-None",
    "etr": "ETR-EXP",
    "etrConfidence": null,
    "cluster": false,
    "comments": "An outage has been reported in your area. We are working to determine a restoration time.",
    "cause": null,
    "numberOut": 1,
    "custAffected": 4,
    "crewStatus": null,
    "startTime": null,
    "latitude": 32.05308,
    "longitude": -81.13452,
    "source": "https://kubra.io/cluster-data/302/f738adb9-3478-457e-9af5-fc3b91ec6aec/4b67048e-c851-4ada-93f3-dfafe53d10ab/public/cluster-2/0320033223203.json"
  },
  {
    "id": "yq|bE~pinN-None",
    "etr": "2025-08-06T07:30:00Z",
    "etrConfidence": null,
    "cluster": false,
    "comments": "An outage has been reported in your area. We are working to determine a restoration time.",
    "cause": null,
    "numberOut": 1,
    "custAffected": 4,
    "crewStatus": null,
    "startTime": null,
    "latitude": 32.10029,
    "longitude": -81.15488,
    "source": "https://kubra.io/cluster-data/322/f738adb9-3478-457e-9af5-fc3b91ec6aec/4b67048e-c851-4ada-93f3-dfafe53d10ab/public/cluster-2/0320033223.json"
  },
  {
    "id": "sxubEfbcnN-None",
    "etr": "2025-08-06T06:30:00Z",
    "etrConfidence": null,
    "cluster": false,
    "comments": "An outage has been reported in your area. We are working to determine a restoration time.",
    "cause": null,
    "numberOut": 1,
    "custAffected": 16,
    "crewStatus": null,
    "startTime": null,
    "latitude": 32.06554,
    "longitude": -81.1218,
    "source": "https://kubra.io/cluster-data/012/f738adb9-3478-457e-9af5-fc3b91ec6aec/4b67048e-c851-4ada-93f3-dfafe53d10ab/public/cluster-2/0320033223210.json"
  },
  {
    "id": "ahwbEz~bnN-None",
    "etr": "2025-08-06T13:00:00Z",
    "etrConfidence": null,
    "cluster": false,
    "comments": "An outage has been reported in your area. We are working to determine a restoration time.",
    "cause": null,
    "numberOut": 1,
    "custAffected": 4,
    "crewStatus": null,
    "startTime": null,
    "latitude": 32.07313,
    "longitude": -81.12126,
    "source": "https://kubra.io/cluster-data/012/f738adb9-3478-457e-9af5-fc3b91ec6aec/4b67048e-c851-4ada-93f3-dfafe53d10ab/public/cluster-2/0320033223210.json"
  },
  {
    "id": "euizDfk{zN-None",
    "etr": "2025-08-06T06:00:00Z",
    "etrConfidence": null,
    "cluster": false,
    "comments": "An outage has been reported in your area. We are working to determine a restoration time.",
    "cause": null,
    "numberOut": 1,
    "custAffected": 24,
    "crewStatus": null,
    "startTime": null,
    "latitude": 30.69283,
    "longitude": -83.2122,
    "source": "https://kubra.io/cluster-data/012/f738adb9-3478-457e-9af5-fc3b91ec6aec/4b67048e-c851-4ada-93f3-dfafe53d10ab/public/cluster-2/0320210.json"
  }
]