[
  {
    "id": "s_vpEbwfyN-None",
    "etr": "ETR-EXP",
    "etrConfidence": null,
    "cluster": true,
    "comments": null,
    "cause": null,
    "numberOut": 2,
    "custAffected": 7,
    "crewStatus": null,
    "startTime": null,
    "latitude": 34.36042,
    "longitude": -82.94274,
    "source": "https://kubra.io/cluster-data/302/f738adb9-3478-457e-9af5-fc3b91ec6aec/8cb2c259-5ce3-4ce1-b154-2ed28107a3b5/public/cluster-2/03200303222203.json"
  },
  {
    "id": "_tm}DxtppN-None",
    "etr": "2024-12-16T01:00:00Z",
    "etrConfidence": null,
    "cluster": false,
    "comments": "An outage has been reported in your area. We are working to determine a restoration time.",
    "cause": null,
    "numberOut": 1,
    "custAffected": 4,
    "crewStatus": null,
    "startTime": null,
    "latitude": 31.20464,
    "longitude": -81.51901,
    "source": "https://kubra.io/cluster-data/112/f738adb9-3478-457e-9af5-fc3b91ec6aec/8cb2c259-5ce3-4ce1-b154-2ed28107a3b5/public/cluster-2/0320211.json"
  },
  {
    "id": "gmgqEhrc}N-None",
    "etr": "ETR-EXP",
    "etrConfidence": null,
    "cluster": false,
    "comments": "An outage has been reported in your area. We are working to determine a restoration time.",
    "cause": null,
    "numberOut": 1,
    "custAffected": 4,
    "crewStatus": null,
    "startTime": null,
    "latitude": 34.44964,
    "longitude": -83.58197,
    "source": "https://kubra.io/cluster-data/030/f738adb9-3478-457e-9af5-fc3b91ec6aec/8cb2c259-5ce3-4ce1-b154-2ed28107a3b5/public/cluster-2/0320030.json"
  },
  {
    "id": "u}cnEjne|N-None",
    "etr": "2024-12-16T00:00:00Z",
    "etrConfidence": null,
    "cluster": false,
    "comments": "An outage has been reported in your area. We are working to determine a restoration time.",
    "cause": null,
    "numberOut": 1,
    "custAffected": 89,
    "crewStatus": null,
    "startTime": null,
    "latitude": 33.94027,
    "longitude": -83.42774,
    "source": "https://kubra.io/cluster-data/102/f738adb9-3478-457e-9af5-fc3b91ec6aec/8cb2c259-5ce3-4ce1-b154-2ed28107a3b5/public/cluster-2/032003201.json"
  },
  {
    "id": "{`onEzqw{N-None",
    "etr": "ETR-EXP",
    "etrConfidence": null,
    "cluster": false,
    "comments": "An outage has been reported in your area. We are working to determine a restoration time.",
    "cause": null,
    "numberOut": 1,
    "custAffected": 4,
    "crewStatus": null,
    "startTime": null,
    "latitude": 33.9971,
    "longitude": -83.35662,
    "source": "https://kubra.io/cluster-data/102/f738adb9-3478-457e-9af5-fc3b91ec6aec/8cb2c259-5ce3-4ce1-b154-2ed28107a3b5/public/cluster-2/032003201.json"
  },
  {
    "id": "ytorE`bubO-None",
    "etr": "2024-12-16T02:00:00Z",
    "etrConfidence": null,
    "cluster": false,
    "comments": "An outage has been reported in your area. We are working to determine a restoration time.",
    "cause": null,
    "numberOut": 1,
    "custAffected": 46,
    "crewStatus": null,
    "startTime": null,
    "latitude": 34.65565,
    "longitude": -84.49073,
    "source": "https://kubra.io/cluster-data/120/f738adb9-3478-457e-9af5-fc3b91ec6aec/8cb2c259-5ce3-4ce1-b154-2ed28107a3b5/public/cluster-2/0320021.json"
  },
  {
    "id": "m{jmEjsjbO-None",
    "etr": "2024-12-16T01:30:00Z",
    "etrConfidence": null,
    "cluster": false,
    "comments": "An outage has been reported in your area. We are working to determine a restoration time.",
    "cause": null,
    "numberOut": 1,
    "custAffected": 4,
    "crewStatus": null,
    "startTime": null,
    "latitude": 33.81191,
    "longitude": -84.43718,
    "source": "https://kubra.io/cluster-data/132/f738adb9-3478-457e-9af5-fc3b91ec6aec/8cb2c259-5ce3-4ce1-b154-2ed28107a3b5/public/cluster-2/03200231.json"
  },
  {
    "id": "}psmEp{scO-None",
    "etr": "2024-12-16T01:00:00Z",
    "etrConfidence": null,
    "cluster": false,
    "comments": "An outage has been reported in your area. We are working to determine a restoration time.",
    "cause": null,
    "numberOut": 1,
    "custAffected": 4,
    "crewStatus": null,
    "startTime": null,
    "latitude": 33.85631,
    "longitude": -84.64841,
    "source": "https://kubra.io/cluster-data/132/f738adb9-3478-457e-9af5-fc3b91ec6aec/8cb2c259-5ce3-4ce1-b154-2ed28107a3b5/public/cluster-2/03200231.json"
  },
  {
    "id": "}utoEtqybO-None",
    "etr": "2024-12-16T00:45:00Z",
    "etrConfidence": null,
    "cluster": false,
    "comments": "An outage has been reported in your area. We are working to determine a restoration time.",
    "cause": null,
    "numberOut": 1,
    "custAffected": 4,
    "crewStatus": null,
    "startTime": null,
    "latitude": 34.18991,
    "longitude": -84.51371,
    "source": "https://kubra.io/cluster-data/320/f738adb9-3478-457e-9af5-fc3b91ec6aec/8cb2c259-5ce3-4ce1-b154-2ed28107a3b5/public/cluster-2/0320023.json"
  },
  {
    "id": "{g|bEbreaO-None",
    "etr": "2024-12-16T01:00:00Z",
    "etrConfidence": null,
    "cluster": false,
    "comments": "An outage has been reported in your area. We are working to determine a restoration time.",
    "cause": null,
    "numberOut": 1,
    "custAffected": 31,
    "crewStatus": null,
    "startTime": null,
    "latitude": 32.0987,
    "longitude": -84.24754,
    "source": "https://kubra.io/cluster-data/230/f738adb9-3478-457e-9af5-fc3b91ec6aec/8cb2c259-5ce3-4ce1-b154-2ed28107a3b5/public/cluster-2/0320032.json"
  },
  {
    "id": "chz`E~guuN-None",
    "etr": "2024-12-16T01:00:00Z",
    "etrConfidence": null,
    "cluster": false,
    "comments": "An outage has been reported in your area. We are working to determine a restoration time.",
    "cause": null,
    "numberOut": 1,
    "custAffected": 4,
    "crewStatus": null,
    "startTime": null,
    "latitude": 31.76082,
    "longitude": -82.36176,
    "source": "https://kubra.io/cluster-data/012/f738adb9-3478-457e-9af5-fc3b91ec6aec/8cb2c259-5ce3-4ce1-b154-2ed28107a3b5/public/cluster-2/0320210.json"
  },
  {
    "id": "cqgaEdzcqN-None",
    "etr": "2024-12-16T00:00:00Z",
    "etrConfidence": null,
    "cluster": false,
    "comments": "An outage has been reported in your area. We are working to determine a restoration time.",
    "cause": null,
    "numberOut": 1,
    "custAffected": 4,
    "crewStatus": null,
    "startTime": null,
    "latitude": 31.82882,
    "longitude": -81.61715,
    "source": "https://kubra.io/cluster-data/012/f738adb9-3478-457e-9af5-fc3b91ec6aec/8cb2c259-5ce3-4ce1-b154-2ed28107a3b5/public/cluster-2/0320210.json"
  },
  {
    "id": "i~|hE`dztN-None",
    "etr": "2024-12-16T03:00:00Z",
    "etrConfidence": null,
    "cluster": false,
    "comments": "An outage has been reported in your area. We are working to determine a restoration time.",
    "cause": null,
    "numberOut": 1,
    "custAffected": 4,
    "crewStatus": null,
    "startTime": null,
    "latitude": 33.08533,
    "longitude": -82.22289,
    "source": "https://kubra.io/cluster-data/323/f738adb9-3478-457e-9af5-fc3b91ec6aec/8cb2c259-5ce3-4ce1-b154-2ed28107a3b5/public/cluster-2/03200323.json"
  },
  {
    "id": "}tjjE~_btN-None",
    "etr": "ETR-EXP",
    "etrConfidence": null,
    "cluster": false,
    "comments": "An outage has been reported in your area. We are working to determine a restoration time.",
    "cause": null,
    "numberOut": 1,
    "custAffected": 4,
    "crewStatus": null,
    "startTime": null,
    "latitude": 33.31935,
    "longitude": -82.09936,
    "source": "https://kubra.io/cluster-data/123/f738adb9-3478-457e-9af5-fc3b91ec6aec/8cb2c259-5ce3-4ce1-b154-2ed28107a3b5/public/cluster-2/03200321.json"
  },
  {
    "id": "mblkEniusN-None",
    "etr": "2024-12-16T01:45:00Z",
    "etrConfidence": null,
    "cluster": false,
    "comments": "An outage has been reported in your area. We are working to determine a restoration time.",
    "cause": null,
    "numberOut": 1,
    "custAffected": 4,
    "crewStatus": null,
    "startTime": null,
    "latitude": 33.49047,
    "longitude": -82.03432,
    "source": "https://kubra.io/cluster-data/123/f738adb9-3478-457e-9af5-fc3b91ec6aec/8cb2c259-5ce3-4ce1-b154-2ed28107a3b5/public/cluster-2/03200321.json"
  }
]